yjsnpy/__init__.py
yjsnpy/tdn.py
yjsnpy-0.1.dist-info/LICENSE
yjsnpy-0.1.dist-info/METADATA
yjsnpy-0.1.dist-info/WHEEL
yjsnpy-0.1.dist-info/top_level.txt
yjsnpy-0.1.dist-info/RECORD
